LICENSE
README.rst
pyproject.toml
setup.py
frozenclass/__init__.py
frozenclass/auto_freeze.py
frozenclass/cache.py
frozenclass/data_controller.py
frozenclass.egg-info/PKG-INFO
frozenclass.egg-info/SOURCES.txt
frozenclass.egg-info/dependency_links.txt
frozenclass.egg-info/top_level.txt
frozenclass/dataparser/__init__.py
frozenclass/dataparser/const.py
frozenclass/dataparser/data_parser.py
frozenclass/dataparser/data_writer.py
frozenclass/dataparser/types_module.py
frozenclass/exceptions/__init__.py
frozenclass/exceptions/no_save.py
frozenclass/exceptions/no_var.py
frozenclass/functions/__init__.py
frozenclass/functions/parse_name.py
tests/test_async_cache.py
tests/test_autosave.py
tests/test_cache.py
tests/test_deep_save_load.py
tests/test_save_bases.py
tests/test_save_load.py