Metadata-Version: 2.1
Name: frozenclass
Version: 0.1.3
Summary: Python module for convenient storage of classes in files.
Home-page: https://github.com/GigantPro/frozenclass
Download-URL: https://github.com/GigantPro/frozenclass/archive/main.zip
Author: GigantPro
Author-email: gigantpro2000@gmail.ru
License: The GPLv3 License (GPLv3)
Classifier: Operating System :: OS Independent
Classifier: Intended Audience :: End Users/Desktop
Classifier: Intended Audience :: Developers
Classifier: Programming Language :: Python
Classifier: Programming Language :: Python :: 3.7
Classifier: Programming Language :: Python :: 3.8
Classifier: Programming Language :: Python :: 3.9
Classifier: Programming Language :: Python :: 3.10
Classifier: Programming Language :: Python :: 3.11
Classifier: Programming Language :: Python :: Implementation :: PyPy
License-File: LICENSE
